<annotation>
	<folder>collactedimages</folder>
	<filename>no. 34c22d43-92c5-11ef-bf7b-80fa5b9862b6.jpg</filename>
	<path>C:\Users\Metehan Sevgil\Desktop\KODLAR\Phyton\RealTimeObjectDetection\Tensorflow\workspace\images\collactedimages\no. 34c22d43-92c5-11ef-bf7b-80fa5b9862b6.jpg</path>
	<source>
		<database>Unknown</database>
	</source>
	<size>
		<width>640</width>
		<height>480</height>
		<depth>3</depth>
	</size>
	<segmented>0</segmented>
	<object>
		<name>no</name>
		<pose>Unspecified</pose>
		<truncated>0</truncated>
		<difficult>0</difficult>
		<bndbox>
			<xmin>114</xmin>
			<ymin>223</ymin>
			<xmax>299</xmax>
			<ymax>365</ymax>
		</bndbox>
	</object>
</annotation>
